LICENSE
MANIFEST.in
README.md
requirements.txt
setup.py
tajer/__init__.py
tajer/checkpointing.py
tajer/utils.py
tajer.egg-info/PKG-INFO
tajer.egg-info/SOURCES.txt
tajer.egg-info/dependency_links.txt
tajer.egg-info/requires.txt
tajer.egg-info/top_level.txt
tajer/distributed/__init__.py
tajer/distributed/distributed_pytorch.py
tajer/distributed/min_DDP_example.py
tajer/log/__init__.py
tajer/log/logger.py
tajer/log/logger_example.py
tajer/nn/__init__.py
tajer/nn/attention.py
tajer/nn/cbam.py
tajer/nn/dsconv.py
tajer/nn/residual.py
tajer/nn/time_embedding.py