Metadata-Version: 2.1
Name: tajer
Version: 1.2.3
Summary: Collection of useful (PyTorch) functions.
Home-page: https://github.com/joh-fischer/tajer
Author: Johannes S. Fischer
License: MIT License
Classifier: Intended Audience :: Developers
Classifier: License :: OSI Approved :: MIT License
Classifier: Programming Language :: Python :: 3.9
License-File: LICENSE
